{
  "sidebarMenu": {
    "links": [{
      "text": "Edit user",
      "icon": "icon-user"
    },{
      "text": "Web Statistics",
      "icon": "icon-stats-bars"
    },{
      "text": "Upload settings",
      "icon": "icon-wrench"
    },{
      "text": "Events",
      "icon": "icon-location"
    }]
  },
  "userWidget": {
    "links": [{
      "id": "views",
      "icon": "icon-eye"
    },{
      "id": "comments",
      "icon": "icon-bubble"
    }],
    "actions": [{
      "id": "likes",
      "icon": "icon-heart"
    }]
  }
}
